cowsee/__main__.py
cowsee/cli.py
cowsee/core.py
cowsee/drawing.py
cowsee/geometry.py
cowsee/grid.py
cowsee-0.1.1.dist-info/METADATA
cowsee-0.1.1.dist-info/WHEEL
cowsee-0.1.1.dist-info/entry_points.txt
cowsee-0.1.1.dist-info/top_level.txt
cowsee-0.1.1.dist-info/RECORD
