Metadata-Version: 2.4
Name: cowsee
Version: 0.1.1
Summary: Visualize geometry data in the command line, along with the famous talking cow.
Requires-Python: >=3.13
Requires-Dist: dask-geopandas>=0.5.0
Requires-Dist: pillow>=11.3.0
